{"algorithm_middling_triangle-number.md":"BUo5M5Xg","algorithm_simple_first.md":"DtcafLOK","algorithm_simple_second.md":"C80xFtz7","home_git_basic-command.md":"BdQ6zAfU","home_git_husky.md":"CJW-CJ7F","home_git_operation.md":"CABulwtt","home_git_tag.md":"DLZjEZ_q","home_htmlandcss_background.md":"R3f4Z8Ph","home_htmlandcss_bfc.md":"CCHaqX9W","home_htmlandcss_grid.md":"B5MTzDwV","home_htmlandcss_iframe.md":"CNTBw3Jb","home_htmlandcss_layout.md":"0RBOEfxs","home_htmlandcss_less.md":"ByWqCI-J","home_htmlandcss_scroll.md":"CmAKHRRB","home_htmlandcss_skill.md":"sAhTYqh2","home_htmlandcss_some-css.md":"DqENdln4","home_http_cache.md":"C8WEBkpv","home_http_https.md":"Bo4iSoTl","home_http_socket.md":"Bjc0nr0K","home_http_tcp.md":"C2coyccw","home_javascript_ajax.md":"CXsHuwtv","home_javascript_arguments.md":"Bl6gBc2i","home_javascript_array-sort.md":"D0CTsSNv","home_javascript_array.md":"70DEEy7Q","home_javascript_async.md":"CKAGvye6","home_javascript_base64.md":"BiPL0o3L","home_javascript_blob.md":"BPmm0AXK","home_javascript_broadcastchannel.md":"YsqhAZP-","home_javascript_call-apply-bind.md":"DQEQjCIc","home_javascript_canvaslines.md":"Bs0i2B7T","home_javascript_chrome.md":"C5qyDqmw","home_javascript_clipboard.md":"CGgMg2xs","home_javascript_closure.md":"DvpNK1FK","home_javascript_copy.md":"B34t9KCH","home_javascript_custom-events.md":"BnsxDWXh","home_javascript_debounce-and-throttle.md":"PLA2_4A6","home_javascript_encryt.md":"twzsWTmJ","home_javascript_esbuild.md":"RVzxNGq8","home_javascript_eventloop.md":"Atesc5xD","home_javascript_fullscreen.md":"fe7WMiXA","home_javascript_gc.md":"C0BFNfP5","home_javascript_high-api.md":"D0cpXfBq","home_javascript_img.md":"sLI7KAFL","home_javascript_number.md":"Dz4eW-LO","home_javascript_object.md":"wRk1tmBc","home_javascript_promise.md":"C_OvIjYv","home_javascript_prototype.md":"Ewjx3M8g","home_javascript_regexp.md":"Cc-H89oS","home_javascript_screen.md":"8DxOv7Al","home_javascript_sort.md":"Cq4Md8iw","home_javascript_this.md":"CRGav-2t","home_javascript_type-change.md":"DirdBj1v","home_javascript_urlsearchparams.md":"CrLm_6iI","home_javascript_v8.md":"CF14LIWi","home_javascript_virtual-scroll.md":"K-RLyT0F","home_javascript_worker.md":"CSxufXFb","home_mini_attentions.md":"CU1ccR4b","home_mini_getuserinfo.md":"BF3VF8hp","home_mini_globaldata.md":"Cm1Ui0X7","home_nginx_install.md":"DwyfgwVL","home_node_get-params.md":"C1SXj12f","home_node_mysql.md":"B_nk6UBW","home_node_nvm.md":"DHGAg5aS","home_node_pm2.md":"BMEQkCci","home_node_server.md":"CxOaVkyw","home_node_update-node.md":"WFqGw0rc","home_other_linux.md":"CvSRQtSl","home_other_mysql-faq.md":"CWSiB9kO","home_other_mysql.md":"DKb4Fez0","home_other_shell.md":"JBzg6Mlu","home_other_sql.md":"CRzUHeg8","home_other_vscodereg.md":"CtEGcEJe","home_python_fun-params.md":"BK8L9ZXQ","home_python_list.md":"BQU7xVyz","home_python_selenium.md":"BK79lpi4","home_react_antd-pit.md":"DaxwQfFG","home_react_cra.md":"vzPl-FkN","home_react_css-module.md":"3kCF2K0-","home_react_echartsmap.md":"BuONRlHS","home_react_hooks.md":"BXbhNgU8","home_react_immer.md":"Ds4MU9o2","home_react_life-cycle.md":"DZiltfDk","home_react_redux-base.md":"08_WHK2y","home_react_redux-middleware.md":"Cv3OBz8Q","home_react_redux-thunk.md":"DVQB_u1w","home_react_uim-ie11.md":"B5xd8wVk","home_react_xlsx2json.md":"c5mlx8lx","home_readme.md":"CoPvipn4","home_typescript_echart.md":"5GDlfbby","home_typescript_generics.md":"BkHZQhrL","home_typescript_logical-operators.md":"CpFmGSaH","home_typescript_type-interface.md":"DkiGxvSc","home_vue_axios.md":"DFQ0Li9D","home_vue_better-scroll.md":"CJLzxYmb","home_vue_cicd.md":"CxttSnOf","home_vue_component-communication.md":"UKG4Ie2g","home_vue_fastclick.md":"BDHeg1fF","home_vue_lazy-router.md":"BiZFtQ9q","home_vue_nexttick-set.md":"CRmuyxlx","home_vue_persistedstate.md":"Bnh6XLKu","home_vue_px2rem.md":"B_KcYakA","home_vue_px2vw.md":"BJMSWum9","home_vue_revise-style.md":"D0dbULLF","home_vue_route-params.md":"DOYvXOrn","home_vue_router-type.md":"DE53DkrF","home_vue_standard.md":"-a1uZwPd","home_vue_swiper.md":"FYdgewdu","home_vue_vuex.md":"zj__Xu6p","home_vue_watch.md":"CFRQg1O3","home_webpack_babel.md":"DrSkAPEX","home_webpack_handle-css.md":"Q1KpgCwT","home_webpack_loader-plugin.md":"CQQSW5wI","home_webpack_optimize.md":"BhRqsgQn","home_webpack_pack-multiple-js.md":"Bx4P2xuF","home_webpack_processenv.md":"pno_9an0","home_webpack_start-gzip.md":"Di8iZDVy","home_webpack_toes6.md":"B9RsK7Fl","home_webpack_tree-shaking.md":"BSPWTpd2","index.md":"BTUKliyw","interview_subject_css.md":"LVqy9UZ0","interview_subject_js.md":"DbKWyOI1","interview_subject_react.md":"Bg5kSKHz","interview_subject_vue.md":"CLf1UoCh","literature_sentence.md":"CGALsOLo","others_dir_computer-binary.md":"BL_60vrC","others_dir_jenkins.md":"DeUHmMtz","others_dir_markdown.md":"Bhz9VcQL","others_dir_npm-error.md":"CW58YaI4","others_dir_npm.md":"BxRw5bdy","others_dir_publish-npm.md":"DhmMfQQz","others_dir_refresh-origin.md":"1k6xV15Y","others_dir_repair.md":"PpQQw9xx","others_dir_rules.md":"0VVVGb00","others_dir_script.md":"BwtSBApv","others_dir_vuepress-deploy.md":"BRUC47qN","others_dir_whistle.md":"v8vrFgas","others_dir_yarn-update.md":"XT04WW3H","others_mac_cannotopen.md":"D1X8Iggy","others_mac_link-server.md":"DmyoGdHH","others_mac_setting-ssh.md":"gX5Lnsjs"}
